npllm/core/__init__.py
npllm/core/call_llm.py
npllm/core/call_site.py
npllm/core/llm.py
npllm/core/type.py
npllm/core/prompts/system_prompt_template.md
npllm/core/prompts/user_prompt_template.md
npllm/utils/__init__.py
npllm/utils/notebook_util.py
npllm/utils/source_util.py
npllm-0.1.2.dist-info/METADATA
npllm-0.1.2.dist-info/WHEEL
npllm-0.1.2.dist-info/licenses/LICENSE
npllm-0.1.2.dist-info/RECORD
