Metadata-Version: 2.4
Name: npllm
Version: 0.1.2
Summary: No Prompt For LLM
Author-email: renjiyun <wozaijixu@msn.cn>
License-File: LICENSE
Requires-Python: >=3.10
Requires-Dist: jupyterlab>=4.4.7
Requires-Dist: litellm>=1.77.1
